CHANGES.txt
LICENSE.txt
MANIFEST.in
README.md
pyproject.toml
setup.cfg
setup.py
tox.ini
src/pyramid_debugtoolbar_ajax/__init__.py
src/pyramid_debugtoolbar_ajax.egg-info/PKG-INFO
src/pyramid_debugtoolbar_ajax.egg-info/SOURCES.txt
src/pyramid_debugtoolbar_ajax.egg-info/dependency_links.txt
src/pyramid_debugtoolbar_ajax.egg-info/not-zip-safe
src/pyramid_debugtoolbar_ajax.egg-info/requires.txt
src/pyramid_debugtoolbar_ajax.egg-info/top_level.txt
src/pyramid_debugtoolbar_ajax/panels/__init__.py
src/pyramid_debugtoolbar_ajax/panels/ajax.py
src/pyramid_debugtoolbar_ajax/panels/templates/ajax.dbtmako
tests/test_config.py