Metadata-Version: 2.1
Name: pyramid-debugtoolbar-ajax
Version: 0.1.5
Summary: Ajax support for pyramid_debugtoolbar
Home-page: https://github.com/jvanasco/pyramid_debugtoolbar_ajax
Author: Jonathan Vanasco
Author-email: jonathan@findmeon.com
License: MIT
Keywords: web pyramid ajax debug
Platform: UNKNOWN
Classifier: Intended Audience :: Developers
Classifier: Framework :: Pyramid
Classifier: Programming Language :: Python
Classifier: Programming Language :: Python :: 2
Classifier: Programming Language :: Python :: 3
Classifier: License :: OSI Approved :: MIT License
Provides-Extra: testing
